cson/__init__.py
cson/parser.py
cson/writer.py
cson-0.8.dist-info/LICENSE
cson-0.8.dist-info/METADATA
cson-0.8.dist-info/WHEEL
cson-0.8.dist-info/top_level.txt
cson-0.8.dist-info/RECORD
